Metadata-Version: 2.1
Name: LogsHub
Version: 1.2.0
Summary: Writing specific logs
Home-page: https://github.com/Odai-Atef/logs_hub_python3
Author: Odai
Author-email: o.3odai@gmail.com
License: OpenSource
Classifier: Development Status :: 3 - Alpha
Classifier: Intended Audience :: Developers
Classifier: Topic :: Software Development :: Build Tools
Classifier: Programming Language :: Python :: 3
Classifier: Programming Language :: Python :: 3.4
Classifier: Programming Language :: Python :: 3.5
Classifier: Programming Language :: Python :: 3.6
License-File: LICENSE.txt
